perceptualtests/__init__.py
perceptualtests/baselines.py
perceptualtests/campbell_robson_test.py
perceptualtests/color_matrices.py
perceptualtests/colored_squares.py
perceptualtests/gabor_test.py
perceptualtests/matching.py
perceptualtests/receptive_fields.py
perceptualtests/stimuli.py
perceptualtests/tests.py
perceptualtests/utils.py
perceptualtests/data/cmf_ciexyz.mat
perceptualtests-0.1.0.dist-info/METADATA
perceptualtests-0.1.0.dist-info/WHEEL
perceptualtests-0.1.0.dist-info/top_level.txt
perceptualtests-0.1.0.dist-info/RECORD
