Metadata-Version: 2.1
Name: perceptualtests
Version: 0.1.0
Summary: A module to test perceptual factors of deep learning models.
Home-page: https://github.com/Jorgvt/PerceptualTests
Author: Jorge Vila Tomás
Author-email: jorge.vila-tomas@uv.es
License: BSD 2-clause
